Workbook

Sheet Read me
A1: Cotera Problem-to-Agent Library
A3: What this is | B3: Every problem statement from Cotera Booth Bingo, each mapped to a drafted agent, workflow or dataset that solves it. Overlapping problems share one solution. Drafts are starting points: tailor them with the attendee's context, then build them in Cotera.
A4: How to use it | B4: When an attendee picks a problem, find it on the Problems tab (filter by card text or ID). It names the solution, explains how it solves that specific problem, and gives a question to ask them. The full spec is on the Agents tab.
A5: Agents tab | B5: One row per solution: what it does, how it works, data it uses, who uses it, a small first version, how to measure it, and a discovery question.
A6: Problems tab | B6: One row per problem statement with its solution. Use the Agent ID to find the full spec on the Agents tab.
A7: By role tab | B7: The full list grouped by role, so each persona sees every problem that applies to it (problems shared by roles appear under each).
A8: "(to confirm)" | B8: Marks private data, integrations, CRM write-back or permissions that must be confirmed for each deployment. First versions produce outputs a person reviews before anything is changed or sent.
A9: Retired roles | B9: Support & customer experience and Risk, fraud & payments were removed from the game. Their problems are included and marked "No (retired role)" so you can filter them out.
A10: Cotera wedges | B10: W1 Account Targeting · W2 Buyer Readiness · W3 Customer Risk & Growth · W4 Market Intelligence · W5 Operational Intelligence · Platform = controls for running agents safely. Source: Cotera Persona Wedge Doc.
A11: Solutions | B11: =COUNTA(Agents!A2:A500)
A12: Problem statements | B12: =COUNTA(Problems!A2:A500)
A13: Problems in the current game | B13: =COUNTIF(Problems!E2:E500,"Yes")

Sheet Agents
A1: Agent ID | B1: Agent name | C1: Type | D1: Cotera wedge | E1: Roles | F1: In current game | G1: Problems solved (#) | H1: Problems solved | I1: What it does | J1: How it works | K1: Data it uses | L1: Who uses it | M1: First version | N1: How we'd measure it | O1: Ask them
A2: A01 | B2: Contact Data Freshness | C2: Agent | D2: W1 | E2: Sales & prospecting, Revenue & marketing ops, Customer success & accounts | F2: Yes | G2: =COUNTIF(Problems!G$2:G$500,A2) | H2: • Need better contact data • Wrong job titles in the contact list • Cold emails keep bouncing • Contact changed jobs. CRM didn't. | I2: Checks contacts before anyone reaches out, finds missing or out-of-date emails, phone numbers, job titles and employers, and proposes corrections with a source for each, so reps reach the right people. | J2: A rep uploads a prospect list, or a weekly check runs on CRM contacts (to confirm) → the agent compares each person's title and employer with public profiles, company team pages and announcements, and checks that each email domain can receive mail → it marks every field confirmed, changed or unknown, with the source and date → an ops owner reviews the proposed corrections before anything is written back to the CRM. | K2: Public profiles, company team pages, announcements and email domain records; CRM contacts, bounce history from the sending tool, and any data vendor or email checker already in use (to confirm). | L2: RevOps owns the checks and approves CRM updates; SDRs and AEs get corrected lists before outreach starts; CSMs hear when a client contact has moved. | M2: Check one rep's next 200 prospects plus last month's bounced emails, marking each field confirmed, changed or unknown, and compare the results with what the rep finds by hand. | N2: Bounce rate on checked lists against unchecked ones; share of proposed corrections the ops owner approves unchanged. | O2: When a contact detail turns out to be wrong, how do you usually find out?
A3: A02 | B3: Account Research Brief | C3: Agent | D3: W1 / W2 | E3: Sales & prospecting, Marketing & growth, Strategy & market intelligence | F3: Yes | G3: =COUNTIF(Problems!G$2:G$500,A3) | H3: • Too much tab switching for account research • Client priorities changed. Our brief didn't. | I3: Builds a one-page brief on any account before a rep touches it, and refreshes it before each client conversation, so the research happens once, stays current, and lands where the team already works. | J3: Someone names an account, or a client meeting is booked (calendar to confirm) → the agent reads the company's site, news, job posts and public profiles, plus CRM history and notes (to confirm) → it writes a brief with ICP fit, likely buying roles, recent changes and a suggested angle, each line sourced and dated → before each meeting it re-checks and leads with what changed, in the account record or Slack (to confirm). | K3: Public web, news, job posts and profiles; CRM account and activity history, past meeting notes and calendar (access to confirm). | L3: SDRs and AEs read it before outreach; account leads and partners read the refreshed version before client meetings; the sales manager spot-checks quality. | M3: Briefs for 25 accounts from one rep's list, compared side by side with that rep's own research, plus refreshed briefs for five upcoming client meetings, checked by whoever runs each meeting. | N3: Research minutes per account before and after; share of briefs reps rate "usable as is"; client meetings where the brief missed a change the client raised. | O3: Which three tabs do you open first, and what are you looking for in each?
A4: A03 | B4: ICP Fit & Shared Target List | C4: Agent | D4: W1 | E4: Sales & prospecting, Revenue & marketing ops, Marketing & growth | F4: Yes | G4: =COUNTIF(Problems!G$2:G$500,A4) | H4: • Still guessing which accounts to target • Building account lists by hand • Missing company details in the CRM • Sales and marketing disagree on priority accounts | I4: Turns your best customers into written fit criteria, finds and scores companies that match, fills in missing company facts, and builds one ranked target list that sales and marketing both work from, with the reason behind every score. | J4: Sales and marketing agree fit criteria, drafted from past wins and losses (to confirm) → the agent finds matching companies on the public web and fills in size, industry, location and other agreed fields → it scores each account, showing which criteria it met, missed or couldn't check, and proposes a priority tier and owner → both teams review one shared list; approved fields go back to the CRM only after sign-off (to confirm). | K4: Past won and lost deals and CRM account fields (to confirm); public company websites, job posts, news and business registries for size, industry and location. | L4: RevOps owns the criteria and the list; sales and marketing leaders agree priority tiers together; SDRs and AEs work the accounts while campaigns target the same list. | M4: A read-only scored list of 200 accounts, half already in the CRM with blank fields and half newly found, reviewed in one session by a sales lead and a marketing lead. | N4: Hours spent building lists before and after; share of listed accounts both teams accept; meeting rate on top-tier accounts compared with the rest. | O4: Which current customers would you clone, and what do they have in common?
A5: A04 | B5: Buying Group Mapper | C5: Agent | D5: W1 / W2 | E5: Sales & prospecting, Marketing & growth | F5: Yes | G5: =COUNTIF(Problems!G$2:G$500,A5) | H5: • Missing contacts on the buying team • Right company. Wrong department. • Can't find who signs off on the deal | I5: Maps who is likely involved in a purchase at an account: the team that owns the problem, the people who shape the choice, and who can approve the spend, with the evidence and confidence for each. | J5: A rep names an account or an open deal → the agent reads public profiles, team pages, job posts and announcements, plus CRM contacts and call notes (to confirm) → it identifies the department that owns the problem you solve and lists likely users, evaluators and approvers, each marked confirmed, inferred or unknown → the rep reviews the map and chooses who to contact; nothing is added to the CRM without approval. | K5: Public profiles, company team pages, job posts and leadership announcements; CRM contacts, call notes and who signed past deals (to confirm). | L5: AEs and SDRs use it on target accounts and open deals; sales managers use it in deal reviews; marketing uses the role list for campaigns aimed at those accounts. | M5: Maps for 15 open deals, checked by each deal owner, plus 10 closed deals to see whether it would have found the person who actually signed. | N5: Share of mapped roles reps confirm as correct; deals where the approver was named before the proposal went out. | O5: On your last won deal, who was involved that you didn't know about at the start?
A6: A05 | B6: Buyer Readiness Signals | C6: Agent | D6: W2 | E6: Sales & prospecting, Marketing & growth | F6: Yes | G6: =COUNTIF(Problems!G$2:G$500,A6) | H6: • Intent isn't intenting • Intent alerts with no clue what triggered them • Our outreach arrives after the buying decision • Sales alerts nobody has time to read • A website visit doesn't mean 'call me' | I6: Combines intent data, website visits and public buying signals into one short, dated note per account that explains what triggered it, then recommends a play that fits how ready the account looks, so reps see only the few worth acting on now. | J6: Daily, the agent collects intent alerts, website visits and CRM activity (to confirm), plus public signals like hiring, funding and leadership changes → it groups them by account and checks them against each other and the account's fit → it writes one note per account: what happened, when, what it may mean and what's still unknown → each rep gets a short ranked list with a suggested play: call, send something useful, or wait. | K6: Intent data feeds, website visit data, marketing engagement and CRM activity (all to confirm); public job posts, news, funding announcements and leadership changes. | L6: Marketing ops or RevOps owns the signal rules; SDRs and AEs work the ranked list; marketing handles accounts not yet ready; sales leaders check which signals led to meetings. | M6: Run it on last quarter's intent alerts and website visits to see which accounts it would have ranked highest, and compare them with the accounts that actually opened a deal. | N6: Share of recommended calls that become real buying conversations; account alerts each rep receives per week, before and after. | O6: Thinking of your last good deal, what was the first sign they were ready, and who saw it?
A7: A06 | B7: Inbound Lead Response | C7: Workflow | D7: W1 | E7: Sales & prospecting, Marketing & growth | F7: Yes | G7: =COUNTIF(Problems!G$2:G$500,A7) | H7: • Gotta be quicker with inbound leads • Different lead sources. Same follow-up. | I7: Gives every inbound lead a fast first reply that fits how they found you: it researches the person, labels the source and request, and drafts a matching response for a rep to approve while the request is still fresh. | J7: A demo request, form fill, referral or ad response arrives (sources to confirm) → the workflow checks the person and company against public sources and the CRM (to confirm), and labels the source and request → it drafts a reply to match: a booking link for demo requests, a note naming the referrer for referrals, a useful resource for ad responses → the rep approves or edits it, and leads still waiting are flagged. | K7: Form submissions, demo requests, referral notes and ad campaign details, plus CRM records (all to confirm); public company and profile information. | L7: Marketing ops owns the source rules and reply templates; SDRs or AEs approve and send; the sales manager watches response times. | M7: Two weeks on demo requests and referrals only, with every draft approved by a rep and the time to first reply logged for each lead. | N7: Time from inbound request to first reply, before and after; meeting rate by lead source. | O7: When someone fills in your demo form, what happens next, and how long does it take?
A8: A07 | B8: Lead Intake & Routing Checker | C8: Workflow | D8: W1 | E8: Revenue & marketing ops | F8: Yes | G8: =COUNTIF(Problems!G$2:G$500,A8) | H8: • New leads keep landing with the wrong rep • The same account assigned to two reps • Lead routing rules nobody understands • New leads wait on spreadsheet imports | I8: Checks every new lead before it reaches a rep: matches it to the right account and owner, tests the assignment against your territory rules written in plain English, and flags wrong or double ownership with the reason. | J8: New leads arrive from forms, events or spreadsheet uploads (sources to confirm) → the workflow checks required fields, matches each lead to an existing account and owner, and fills gaps from public company data → it compares the assigned rep with the plain-English territory rules and flags mismatches and accounts with two owners → an ops owner reviews the flags; routing changes go live only after approval. | K8: Lead forms and import files, CRM accounts, owners and assignment history, current routing rules and territory list (all to confirm); public company data for region and size. | L8: RevOps owns the rules and reviews flags; sales managers settle ownership conflicts; reps see why each lead came to them. | M8: Run last month's leads through it read-only: rewrite the current rules in plain English, then list every lead that would have gone to a different rep and every account with two owners. | N8: Share of leads reassigned after first routing; time from lead arrival to rep assignment; number of accounts with more than one owner. | O8: When a lead goes to the wrong rep, how do you find out, and who fixes it?
A9: A08 | B9: Explainable Lead Score | C9: Agent + dataset | D9: W1 | E9: Revenue & marketing ops | F9: Yes | G9: =COUNTIF(Problems!G$2:G$500,A9) | H9: • A lead score nobody can explain | I9: Gives every lead score a plain-English reason: which facts raised or lowered it, where each fact came from and what's still unknown, and keeps a dataset showing which scores turned into real opportunities. | J9: A new lead arrives with its current score (to confirm) → the agent scores it against criteria written in plain English, like company fit, role and recent activity, and lists what raised or lowered it, each with its source → it notes missing data and where its view differs from the current score → the dataset records each score, its reasons and the outcome, and RevOps reviews monthly which reasons predicted real deals. | K9: Lead and contact fields, the current scoring model and its inputs, marketing engagement and CRM outcomes (all to confirm); public company and role data. | L9: RevOps owns the criteria and dataset; SDRs read the reasons before working a lead; sales and marketing leaders approve any change to the criteria. | M9: Score last quarter's leads both ways, with reasons shown for each, and compare which ranking better matched the leads that became opportunities, before scoring any live leads. | N9: Opportunity rate of top-ranked leads compared with the current score; share of score reasons reps rate as accurate. | O9: Pick your top-scored lead this week: can anyone say why it ranks above the next one?
A10: A09 | B10: Campaign Audience Guard | C10: Workflow | D10: W1 | E10: Sales & prospecting, Marketing & growth, Customer success & accounts, Revenue & marketing ops | F10: Yes | G10: =COUNTIF(Problems!G$2:G$500,A10) | H10: • Still emailing people who already said no • Existing clients treated like brand-new leads • Unsubscribed contacts back in the campaign | I10: Checks every outreach list and automated follow-up against declines, opt-outs and current customers before messages go out, and flags anyone who shouldn't be contacted, with the reason, for a person to review. | J10: A list is imported or an automated follow-up is due to send (tools to confirm) → the workflow checks each person against opt-outs from every tool and current customer accounts → it reads recent replies for clear no's, like 'not interested' or 'please stop', even when nobody marked them → it lists flagged people with the reason; an ops owner reviews, and automatic holds start only once the checks prove accurate. | K10: Outreach and email tool lists, sequences and replies; unsubscribe and do-not-contact lists; CRM customer accounts and contacts; import files (all to confirm). | L10: RevOps or marketing ops owns the checks; reps and marketers see why each person was flagged; CS confirms customer matches. | M10: A read-only check of all running email sequences and the last three list imports, listing everyone who declined, opted out or already buys from you, with a sample checked by hand. | N10: People flagged before a message went out; opt-out complaints and already-a-customer replies per month, before and after. | O10: When someone says no or opts out in one tool, how does every other tool find out?
A11: A10 | B11: Personalized Outreach Writer | C11: Agent | D11: W2 | E11: Sales & prospecting, Marketing & growth | F11: Yes | G11: =COUNTIF(Problems!G$2:G$500,A11) | H11: • Sales emails that could be for anyone • Writing one good sales email takes forever • AI emails that sound like AI emails • Good prospect. Nothing relevant to say. | I11: Drafts a short first email for each prospect around one specific, sourced reason to talk now, written in your team's own voice, for a rep to edit and send. | J11: A rep picks a prospect, or one arrives from a target list → the agent reads recent company news, job posts, the person's public posts and role, plus CRM history (to confirm), and picks the most timely reason to reach out → it drafts a short email in the style of your best past emails, citing its source → the rep edits and sends; if no good reason exists, the agent says so. | K11: Public news, job posts, company pages and profiles; your best-performing past emails, messaging guide and CRM history (to confirm). | L11: SDRs and AEs edit and send drafts; marketing owns the voice guide and approved claims; sales managers review a sample of drafts each week. | M11: Drafts for 30 prospects on one rep's list, mixed in with that rep's own emails, so the team can judge relevance and try to spot which ones a tool wrote. | N11: Minutes to produce a send-ready email; reply rate against the rep's usual emails; share of drafts sent with light edits. | O11: What did your best-performing cold email say, and why do you think it worked?
A12: A11 | B12: Cold Call Prep | C12: Agent | D12: W1 / W2 | E12: Sales & prospecting | F12: Yes | G12: =COUNTIF(Problems!G$2:G$500,A12) | H12: • Nobody wants to cold call | I12: Prepares a short call sheet for each prospect in a call block: who they are, why the call is timely, an opener, likely objections with answers, and which number to try, so reps pick up the phone ready. | J12: A rep schedules a call block → the agent picks best-fit prospects with a recent, sourced reason to call, warmest first, and checks which numbers look current (to confirm) → for each it writes a one-page call sheet: why now, an opener, two questions and answers to likely objections → after each call, the rep's quick notes become a draft follow-up and CRM update to approve (to confirm). | K12: Public news, job posts and profiles; the rep's prospect list, CRM history, phone numbers and past call outcomes (to confirm). | L12: SDRs and AEs use the call sheets; the sales manager schedules call blocks and reviews sheet quality; RevOps confirms where call outcomes are logged. | M12: Call sheets for one rep's next 20 calls in a single call block, with the rep noting which sheets helped and which openers started a real conversation. | N12: Calls made per scheduled block before and after; share of calls that become real conversations. | O12: What would a rep need to know before they'd feel ready to pick up the phone?
A13: A12 | B13: Same-Day Event Follow-up | C13: Workflow | D13: W2 | E13: Sales & prospecting, Marketing & growth | F13: Yes | G13: =COUNTIF(Problems!G$2:G$500,A13) | H13: • Event leads go cold before we follow up | I13: Turns a badge scan or booth note into a personal follow-up draft within hours, while the conversation is still remembered. | J13: At the end of each event day, the attendee list or booth notes arrive → each person is matched to their company and to any existing CRM record (to confirm) → the workflow drafts a follow-up that references what was actually discussed, plus one relevant resource → a rep approves or edits it before anything is sent. | K13: Event attendee export, booth or scanner notes and CRM records (all to confirm); public company context. | L13: Field or event marketing owns it; reps approve and send. | M13: Run it on one event's list, with every draft human-approved. | N13: Hours from event to first touch; reply rate against the last comparable event. | O13: How long after an event does the first email usually go out, and who writes it?
... A64: A63 | B64: Fraud Pattern Spotter | C64: Agent | D64: W5 | E64: Risk, fraud & payments | F64: No (retired role) | G64: =COUNTIF(Problems!G$2:G$500,A64) | H64: • Fraud patterns are spotted one case too late | I64: Looks across open and recent cases each day for shared details such as devices, addresses or payment methods, and tells the fraud lead when several cases look connected, while related cases are still open. | J64: Daily, the agent reads new, open and recently closed cases (to confirm) → it groups cases that share details such as a device, address, email pattern or card range, or that follow the same sequence of events → it writes a pattern note: the linked cases, what they share, what is inferred and what is still unknown → the fraud lead confirms the pattern before reviewers are alerted or any rule changes. | K64: Case records and outcomes, transaction details, device, address and account identifiers, reviewer notes (all private, access to confirm). | L64: The fraud lead owns it and confirms each pattern; reviewers get confirmed pattern notes on matching open cases; rule owners decide on rule changes. | M64: Run it on last quarter's cases and check whether it would have linked the patterns your team found by hand, and how many cases sooner. | N64: Cases handled before a pattern was flagged, compared with past patterns; share of pattern notes the fraud lead confirms. | O64: Thinking of the last fraud pattern you caught, which case first made someone suspicious?

Sheet Problems
A1: Problem ID | B1: Card text | C1: Problem statement | D1: Roles | E1: In current game | F1: Shared AI problem | G1: Agent ID | H1: Agent name | I1: How this agent solves it | J1: Ask them about this problem
A2: s1-02 | B2: Need better contact data | C2: Missing or wrong emails, phone numbers, and job titles make it hard to reach the right people. | D2: Sales & prospecting; Revenue & marketing ops | E2: Yes | F2: No | G2: A01 | H2: Contact Data Freshness | I2: Each contact gets a field-by-field check of email, phone and title, with source and date, and anything it can't confirm is marked unknown so reps know what to verify. | J2: Which is wrong or missing most often for you: emails, phone numbers or titles?
A3: s1-03 | B3: Still guessing which accounts to target | C3: There's no reliable way to tell which companies actually need what we sell. | D3: Sales & prospecting | E3: Yes | F3: No | G3: A03 | H3: ICP Fit & Shared Target List | I3: Each account is scored against criteria drawn from your actual wins and losses (to confirm), with the evidence for each point shown, so targeting rests on checkable reasons. | J3: When a deal closed quickly, what was true about that company beforehand?
A4: s1-04 | B4: Too much tab switching for account research | C4: Researching one company means jumping between its website, LinkedIn, the CRM, and other tools. | D4: Sales & prospecting; Marketing & growth | E4: Yes | F4: No | G4: A02 | H4: Account Research Brief | I4: It reads the website, public profiles, news and CRM history (to confirm) in one pass and puts the findings on one page, each line linked to its source. | J4: How long does researching one account take today, and which step takes longest?
A5: s1-06 | B5: Missing contacts on the buying team | C5: We know one person at the account, but we're missing others involved in choosing a product. | D5: Sales & prospecting; Marketing & growth | E5: Yes | F5: No | G5: A04 | H5: Buying Group Mapper | I5: Starting from the one contact you know, it finds their manager, peers and the other teams usually involved in choosing a product, each with its source. | J5: How many people end up involved in a typical deal, and how many do you know early?
A6: s1-08 | B6: Intent isn't intenting | C6: The data says an account is interested, but that interest doesn't turn into a real buying conversation. | D6: Sales & prospecting; Marketing & growth | E6: Yes | F6: No | G6: A05 | H6: Buyer Readiness Signals | I6: It treats an intent score as one clue, recommends a call only when fit and a second sign agree, and tracks which combinations of signs actually led to conversations. | J6: Of the accounts your intent data flagged last quarter, how many became real conversations?
A7: s1-09 | B7: Gotta be quicker with inbound leads | C7: People ask about our product, but we take too long to get back to them. | D7: Sales & prospecting | E7: Yes | F7: No | G7: A06 | H7: Inbound Lead Response | I7: Research and a draft reply are ready when the request arrives, so the rep only reviews and sends, and leads left waiting past an agreed time are flagged. | J7: How long does a new inbound request usually wait before someone replies, and why?
A8: s1-10 | B8: Nobody wants to cold call | C8: Calling someone who hasn't asked to hear from us is the task everyone keeps putting off. | D8: Sales & prospecting | E8: Yes | F8: No | G8: A11 | H8: Cold Call Prep | I8: Each call in a scheduled block comes with a sourced reason the prospect might care now, an opener and objection answers, warmest prospects first. | J8: When a rep skips a call block, what's the usual reason?
A9: s1-11 | B9: Event leads go cold before we follow up | C9: By the time we email someone we met at an event, the conversation is no longer fresh. | D9: Sales & prospecting; Marketing & growth | E9: Yes | F9: No | G9: A12 | H9: Same-Day Event Follow-up | I9: Reps get same-day drafts that mention what was discussed at the booth, so writing no longer delays the first email and the person still remembers the conversation. | J9: What do reps write down after a booth conversation, and where do those notes end up?
A10: s1-12 | B10: Sales emails that could be for anyone | C10: Adding a first name doesn't make the rest of the email relevant to that person's business. | D10: Sales & prospecting; Marketing & growth | E10: Yes | F10: No | G10: A10 | H10: Personalized Outreach Writer | I10: Each email is built around one fact about the prospect's business, such as a new market or a hiring push, and links it to how you help. | J10: Beyond the first name, what does a rep usually change in an email for each prospect?
A11: s1-13 | B11: Great demo. Then we get ghosted. | C11: The demo seems to go well, but the buyer stops replying and there's no agreed next step. | D11: Sales & prospecting; Marketing & growth | E11: Yes | F11: No | G11: A13 | H11: Meeting & Demo Follow-through | I11: After each demo it checks the notes for an agreed, dated next step; if none exists or the buyer goes quiet, the rep gets a recap draft proposing one. | J11: In your last ghosted deal, what had the buyer agreed to do next?
A12: s1-22 | B12: Our competitor notes are already out of date | C12: The comparison sheet still describes an old version of the other product. | D12: Sales & prospecting; Marketing & growth; Strategy & market intelligence | E12: Yes | F12: No | G12: A20 | H12: Competitor Watch | I12: Each line of the comparison sheet carries a source and date; when a competitor page changes, the agent proposes the edit, and lines past their review date are flagged. | J12: Who owns the comparison sheet today, and when was it last updated?
... A172: r-25 | B172: No feedback when a risk alert was wrong | C172: The people maintaining our review rules do not hear which alerts reviewers found unhelpful or incorrect. | D172: Risk, fraud & payments | E172: No (retired role) | F172: No | G172: A60 | H172: Alert Explainer & False-Alarm Filter | I172: Reviewers mark each alert as useful, wrong or unhelpful with a reason, and rule owners get a weekly summary by rule with example cases. | J172: How do the people who write your rules hear what reviewers think of them?

Sheet By role
A1: Role | B1: In current game | C1: Problem ID | D1: Card text | E1: Problem statement | F1: Agent ID | G1: Agent name | H1: How this agent solves it
A2: Sales & prospecting | B2: Yes | C2: s1-02 | D2: Need better contact data | E2: Missing or wrong emails, phone numbers, and job titles make it hard to reach the right people. | F2: A01 | G2: Contact Data Freshness | H2: Each contact gets a field-by-field check of email, phone and title, with source and date, and anything it can't confirm is marked unknown so reps know what to verify.
A3: Sales & prospecting | B3: Yes | C3: s1-03 | D3: Still guessing which accounts to target | E3: There's no reliable way to tell which companies actually need what we sell. | F3: A03 | G3: ICP Fit & Shared Target List | H3: Each account is scored against criteria drawn from your actual wins and losses (to confirm), with the evidence for each point shown, so targeting rests on checkable reasons.
A4: Sales & prospecting | B4: Yes | C4: s1-04 | D4: Too much tab switching for account research | E4: Researching one company means jumping between its website, LinkedIn, the CRM, and other tools. | F4: A02 | G4: Account Research Brief | H4: It reads the website, public profiles, news and CRM history (to confirm) in one pass and puts the findings on one page, each line linked to its source.
A5: Sales & prospecting | B5: Yes | C5: s1-06 | D5: Missing contacts on the buying team | E5: We know one person at the account, but we're missing others involved in choosing a product. | F5: A04 | G5: Buying Group Mapper | H5: Starting from the one contact you know, it finds their manager, peers and the other teams usually involved in choosing a product, each with its source.
A6: Sales & prospecting | B6: Yes | C6: s1-08 | D6: Intent isn't intenting | E6: The data says an account is interested, but that interest doesn't turn into a real buying conversation. | F6: A05 | G6: Buyer Readiness Signals | H6: It treats an intent score as one clue, recommends a call only when fit and a second sign agree, and tracks which combinations of signs actually led to conversations.
A7: Sales & prospecting | B7: Yes | C7: s1-09 | D7: Gotta be quicker with inbound leads | E7: People ask about our product, but we take too long to get back to them. | F7: A06 | G7: Inbound Lead Response | H7: Research and a draft reply are ready when the request arrives, so the rep only reviews and sends, and leads left waiting past an agreed time are flagged.
A8: Sales & prospecting | B8: Yes | C8: s1-10 | D8: Nobody wants to cold call | E8: Calling someone who hasn't asked to hear from us is the task everyone keeps putting off. | F8: A11 | G8: Cold Call Prep | H8: Each call in a scheduled block comes with a sourced reason the prospect might care now, an opener and objection answers, warmest prospects first.
A9: Sales & prospecting | B9: Yes | C9: s1-11 | D9: Event leads go cold before we follow up | E9: By the time we email someone we met at an event, the conversation is no longer fresh. | F9: A12 | G9: Same-Day Event Follow-up | H9: Reps get same-day drafts that mention what was discussed at the booth, so writing no longer delays the first email and the person still remembers the conversation.
A10: Sales & prospecting | B10: Yes | C10: s1-12 | D10: Sales emails that could be for anyone | E10: Adding a first name doesn't make the rest of the email relevant to that person's business. | F10: A10 | G10: Personalized Outreach Writer | H10: Each email is built around one fact about the prospect's business, such as a new market or a hiring push, and links it to how you help.
A11: Sales & prospecting | B11: Yes | C11: s1-13 | D11: Great demo. Then we get ghosted. | E11: The demo seems to go well, but the buyer stops replying and there's no agreed next step. | F11: A13 | G11: Meeting & Demo Follow-through | H11: After each demo it checks the notes for an agreed, dated next step; if none exists or the buyer goes quiet, the rep gets a recap draft proposing one.
A12: Sales & prospecting | B12: Yes | C12: s1-22 | D12: Our competitor notes are already out of date | E12: The comparison sheet still describes an old version of the other product. | F12: A20 | G12: Competitor Watch | H12: Each line of the comparison sheet carries a source and date; when a competitor page changes, the agent proposes the edit, and lines past their review date are flagged.
... A267: Risk, fraud & payments | B267: No (retired role) | C267: s4-25 | D267: Every simple automation needs an engineer | E267: Even a small change to an everyday workflow has to wait for technical help. | F267: A47 | G267: Shared Team Agents | H267: Instructions, templates, lists and thresholds sit in plain-English settings the business owner edits; each change is tested on saved examples, and only new connections need an engineer.
